stream/collectors.py
stream/__init__.py
stream/stream.py
simplestream-0.1.0.dist-info/RECORD
simplestream-0.1.0.dist-info/metadata.json
simplestream-0.1.0.dist-info/WHEEL
simplestream-0.1.0.dist-info/DESCRIPTION.rst
simplestream-0.1.0.dist-info/top_level.txt
simplestream-0.1.0.dist-info/METADATA
